odoo9_addon_medical_prescription_us-9.0.1.0.0.99.dev3-py2.7-nspkg.pth
odoo9_addon_medical_prescription_us-9.0.1.0.0.99.dev3.dist-info/DESCRIPTION.rst
odoo9_addon_medical_prescription_us-9.0.1.0.0.99.dev3.dist-info/METADATA
odoo9_addon_medical_prescription_us-9.0.1.0.0.99.dev3.dist-info/RECORD
odoo9_addon_medical_prescription_us-9.0.1.0.0.99.dev3.dist-info/WHEEL
odoo9_addon_medical_prescription_us-9.0.1.0.0.99.dev3.dist-info/metadata.json
odoo9_addon_medical_prescription_us-9.0.1.0.0.99.dev3.dist-info/namespace_packages.txt
odoo9_addon_medical_prescription_us-9.0.1.0.0.99.dev3.dist-info/top_level.txt
odoo_addons/medical_prescription_us/README.rst
odoo_addons/medical_prescription_us/__init__.py
odoo_addons/medical_prescription_us/__openerp__.py
odoo_addons/medical_prescription_us/demo/medical_medicament_demo.xml
odoo_addons/medical_prescription_us/demo/medical_patient_demo.xml
odoo_addons/medical_prescription_us/demo/medical_patient_medication_demo.xml
odoo_addons/medical_prescription_us/demo/medical_pharmacy_demo.xml
odoo_addons/medical_prescription_us/demo/medical_physician_demo.xml
odoo_addons/medical_prescription_us/demo/medical_prescription_order_demo.xml
odoo_addons/medical_prescription_us/demo/medical_prescription_order_line_demo.xml
odoo_addons/medical_prescription_us/i18n/es_CO.po
odoo_addons/medical_prescription_us/i18n/es_ES.po
odoo_addons/medical_prescription_us/models/__init__.py
odoo_addons/medical_prescription_us/models/medical_prescription_order_line.py
odoo_addons/medical_prescription_us/static/description/icon.png
odoo_addons/medical_prescription_us/tests/__init__.py
odoo_addons/medical_prescription_us/tests/test_medical_prescription_order_line.py
odoo_addons/medical_prescription_us/views/medical_prescription_order_line_view.xml
